php_compiler_py/__init__.py
php_compiler_py/compile_code.py
php_compiler_py-1.0.0.dist-info/LICENSE
php_compiler_py-1.0.0.dist-info/METADATA
php_compiler_py-1.0.0.dist-info/WHEEL
php_compiler_py-1.0.0.dist-info/top_level.txt
php_compiler_py-1.0.0.dist-info/RECORD
