Metadata-Version: 2.1
Name: php-compiler-py
Version: 1.0.0
Summary: A python client for codegyan php compiler API
Classifier: Programming Language :: Python :: 3
Classifier: License :: OSI Approved :: MIT License
Classifier: Operating System :: OS Independent
Requires-Python: >=3.8
License-File: LICENSE
